README.md
setup.py
blackholepy/__init__.py
blackholepy/client.py
blackholepy/cmd.py
blackholepy/message.py
blackholepy.egg-info/PKG-INFO
blackholepy.egg-info/SOURCES.txt
blackholepy.egg-info/dependency_links.txt
blackholepy.egg-info/requires.txt
blackholepy.egg-info/top_level.txt