Metadata-Version: 1.0
Name: blackholepy
Version: 0.0.1
Summary: blackhole python client
Home-page: https://github.com/elephasinvestment.com/blackhole-python
Author: xitongsys
Author-email: xitongsys@gmail.com
License: UNKNOWN
Platform: UNKNOWN
